{
  "": "",
  "Decrement": "Decrement",
  "Increment": "Increment",
  "PROFILE PAGE": "PROFILE PAGE",
  "throw error": "throw error",
  "Ваш возраст": "Ваш возраст",
  "Ваша фамилия": "Ваша фамилия",
  "Ваше имя": "Ваше имя",
  "Введите username": "Введите username",
  "Введите имя пользователя": "Введите имя пользователя",
  "Введите пароль": "Введите пароль",
  "Введите ссылку на аватар": "Введите ссылку на аватар",
  "Ведите ссылку на аватар": "Ведите ссылку на аватар",
  "Войти": "Войти",
  "Вы ввели неправильный логин или пароль": "Вы ввели неправильный логин или пароль",
  "Выйти": "Выйти",
  "Главная": "Главная",
  "Главная страница": "Главная страница",
  "Город": "Город",
  "Короткий язык": "Короткий язык",
  "О сайте": "О сайте",
  "О сайте23dfds": "О сайте23dfds",
  "О сайтеfdhhgfhgfhgf": "О сайтеfdhhgfhgfhgf",
  "Обновить страницу": "Обновить страницу",
  "Отменить": "Отменить",
  "Переключить": "Переключить",
  "Попробуйте обновить страницу": "Попробуйте обновить страницу",
  "Произошла непредвиденная ошибка": "Произошла непредвиденная ошибка",
  "Произошла ошибка при загрузке профиля": "Произошла ошибка при загрузке профиля",
  "Профиль": "Профиль",
  "Редактировать": "Редактировать",
  "Сохранить": "Сохранить",
  "Страница не найдена": "Страница не найдена",
  "Укажите валюту": "Укажите валюту",
  "Укажите страну": "Укажите страну",
  "Форма авторизации": "Форма авторизации",
  "Язык": "Язык"
}
